{
	"backtrace" : 1,
	"backtraceGraph" : 
	{
		"commands" : 
		[
			"add_custom_target"
		],
		"files" : 
		[
			"PX4-Autopilot/CMakeLists.txt"
		],
		"nodes" : 
		[
			{
				"file" : 0
			},
			{
				"command" : 0,
				"file" : 0,
				"line" : 453,
				"parent" : 0
			}
		]
	},
	"dependencies" : 
	[
		{
			"backtrace" : 1,
			"id" : "px4::@fa3a768158441bce8952"
		}
	],
	"id" : "size::@86297cfe4c11f9a6109d",
	"name" : "size",
	"paths" : 
	{
		"build" : "PX4-Autopilot",
		"source" : "PX4-Autopilot"
	},
	"sourceGroups" : 
	[
		{
			"name" : "",
			"sourceIndexes" : 
			[
				0
			]
		},
		{
			"name" : "CMake Rules",
			"sourceIndexes" : 
			[
				1
			]
		}
	],
	"sources" : 
	[
		{
			"backtrace" : 1,
			"isGenerated" : true,
			"path" : "cmake-build-debug/PX4-Autopilot/CMakeFiles/size",
			"sourceGroupIndex" : 0
		},
		{
			"backtrace" : 0,
			"isGenerated" : true,
			"path" : "cmake-build-debug/PX4-Autopilot/CMakeFiles/size.rule",
			"sourceGroupIndex" : 1
		}
	],
	"type" : "UTILITY"
}
