{
	"backtrace" : 4,
	"backtraceGraph" : 
	{
		"commands" : 
		[
			"add_custom_target",
			"include",
			"generate_messages",
			"add_dependencies"
		],
		"files" : 
		[
			"cmake-build-debug/clover/clover/cmake/clover-genmsg.cmake",
			"/opt/ros/noetic/share/genmsg/cmake/genmsg-extras.cmake",
			"clover/clover/CMakeLists.txt"
		],
		"nodes" : 
		[
			{
				"file" : 2
			},
			{
				"command" : 2,
				"file" : 2,
				"line" : 111,
				"parent" : 0
			},
			{
				"command" : 1,
				"file" : 1,
				"line" : 307,
				"parent" : 1
			},
			{
				"file" : 0,
				"parent" : 2
			},
			{
				"command" : 0,
				"file" : 0,
				"line" : 522,
				"parent" : 3
			},
			{
				"command" : 3,
				"file" : 0,
				"line" : 620,
				"parent" : 3
			},
			{
				"command" : 3,
				"file" : 0,
				"line" : 529,
				"parent" : 3
			},
			{
				"command" : 3,
				"file" : 0,
				"line" : 531,
				"parent" : 3
			},
			{
				"command" : 3,
				"file" : 0,
				"line" : 533,
				"parent" : 3
			},
			{
				"command" : 3,
				"file" : 0,
				"line" : 535,
				"parent" : 3
			},
			{
				"command" : 3,
				"file" : 0,
				"line" : 537,
				"parent" : 3
			},
			{
				"command" : 3,
				"file" : 0,
				"line" : 539,
				"parent" : 3
			},
			{
				"command" : 3,
				"file" : 0,
				"line" : 541,
				"parent" : 3
			},
			{
				"command" : 3,
				"file" : 0,
				"line" : 543,
				"parent" : 3
			},
			{
				"command" : 3,
				"file" : 0,
				"line" : 545,
				"parent" : 3
			}
		]
	},
	"dependencies" : 
	[
		{
			"backtrace" : 5,
			"id" : "std_msgs_generate_messages_py::@0eb71bc6d5b12e2a1c2a"
		},
		{
			"backtrace" : 6,
			"id" : "_clover_generate_messages_check_deps_GetTelemetry::@d951652180eb37dc4694"
		},
		{
			"backtrace" : 7,
			"id" : "_clover_generate_messages_check_deps_Navigate::@d951652180eb37dc4694"
		},
		{
			"backtrace" : 8,
			"id" : "_clover_generate_messages_check_deps_NavigateGlobal::@d951652180eb37dc4694"
		},
		{
			"backtrace" : 9,
			"id" : "_clover_generate_messages_check_deps_SetPosition::@d951652180eb37dc4694"
		},
		{
			"backtrace" : 10,
			"id" : "_clover_generate_messages_check_deps_SetVelocity::@d951652180eb37dc4694"
		},
		{
			"backtrace" : 11,
			"id" : "_clover_generate_messages_check_deps_SetAttitude::@d951652180eb37dc4694"
		},
		{
			"backtrace" : 12,
			"id" : "_clover_generate_messages_check_deps_SetRates::@d951652180eb37dc4694"
		},
		{
			"backtrace" : 13,
			"id" : "_clover_generate_messages_check_deps_SetLEDEffect::@d951652180eb37dc4694"
		},
		{
			"backtrace" : 14,
			"id" : "_clover_generate_messages_check_deps_Execute::@d951652180eb37dc4694"
		}
	],
	"id" : "clover_generate_messages_py::@d951652180eb37dc4694",
	"name" : "clover_generate_messages_py",
	"paths" : 
	{
		"build" : "clover/clover",
		"source" : "clover/clover"
	},
	"sourceGroups" : 
	[
		{
			"name" : "",
			"sourceIndexes" : 
			[
				0
			]
		},
		{
			"name" : "CMake Rules",
			"sourceIndexes" : 
			[
				1,
				2,
				3,
				4,
				5,
				6,
				7,
				8,
				9,
				10,
				11
			]
		}
	],
	"sources" : 
	[
		{
			"backtrace" : 4,
			"isGenerated" : true,
			"path" : "cmake-build-debug/clover/clover/CMakeFiles/clover_generate_messages_py",
			"sourceGroupIndex" : 0
		},
		{
			"backtrace" : 0,
			"isGenerated" : true,
			"path" : "cmake-build-debug/clover/clover/CMakeFiles/clover_generate_messages_py.rule",
			"sourceGroupIndex" : 1
		},
		{
			"backtrace" : 0,
			"isGenerated" : true,
			"path" : "cmake-build-debug/devel/lib/python3/dist-packages/clover/srv/_Execute.py.rule",
			"sourceGroupIndex" : 1
		},
		{
			"backtrace" : 0,
			"isGenerated" : true,
			"path" : "cmake-build-debug/devel/lib/python3/dist-packages/clover/srv/_GetTelemetry.py.rule",
			"sourceGroupIndex" : 1
		},
		{
			"backtrace" : 0,
			"isGenerated" : true,
			"path" : "cmake-build-debug/devel/lib/python3/dist-packages/clover/srv/_Navigate.py.rule",
			"sourceGroupIndex" : 1
		},
		{
			"backtrace" : 0,
			"isGenerated" : true,
			"path" : "cmake-build-debug/devel/lib/python3/dist-packages/clover/srv/_NavigateGlobal.py.rule",
			"sourceGroupIndex" : 1
		},
		{
			"backtrace" : 0,
			"isGenerated" : true,
			"path" : "cmake-build-debug/devel/lib/python3/dist-packages/clover/srv/_SetAttitude.py.rule",
			"sourceGroupIndex" : 1
		},
		{
			"backtrace" : 0,
			"isGenerated" : true,
			"path" : "cmake-build-debug/devel/lib/python3/dist-packages/clover/srv/_SetLEDEffect.py.rule",
			"sourceGroupIndex" : 1
		},
		{
			"backtrace" : 0,
			"isGenerated" : true,
			"path" : "cmake-build-debug/devel/lib/python3/dist-packages/clover/srv/_SetPosition.py.rule",
			"sourceGroupIndex" : 1
		},
		{
			"backtrace" : 0,
			"isGenerated" : true,
			"path" : "cmake-build-debug/devel/lib/python3/dist-packages/clover/srv/_SetRates.py.rule",
			"sourceGroupIndex" : 1
		},
		{
			"backtrace" : 0,
			"isGenerated" : true,
			"path" : "cmake-build-debug/devel/lib/python3/dist-packages/clover/srv/_SetVelocity.py.rule",
			"sourceGroupIndex" : 1
		},
		{
			"backtrace" : 0,
			"isGenerated" : true,
			"path" : "cmake-build-debug/devel/lib/python3/dist-packages/clover/srv/__init__.py.rule",
			"sourceGroupIndex" : 1
		}
	],
	"type" : "UTILITY"
}
